db_mcp/__init__.py
db_mcp/config.py
db_mcp/database.py
db_mcp/server.py
db_mcp/tools.py
db_mcp-0.2.0.dist-info/METADATA
db_mcp-0.2.0.dist-info/WHEEL
db_mcp-0.2.0.dist-info/entry_points.txt
db_mcp-0.2.0.dist-info/top_level.txt
db_mcp-0.2.0.dist-info/RECORD
