Metadata-Version: 2.4
Name: db-mcp
Version: 0.2.0
Summary: Universal MCP server for connecting Claude to SQL databases
Home-page: https://github.com/fenil210/Database-MCP
Author: DB-MCP Contributors
Author-email: fenilramoliya2103@gmail.com
Project-URL: Bug Reports, https://github.com/fenil210/Database-MCP/issues
Project-URL: Source, https://github.com/fenil210/Database-MCP
Project-URL: Documentation, https://github.com/fenil210/Database-MCP/blob/main/README.md
Keywords: mcp,database,sql,claude,ai,postgresql,mysql,sqlite,sqlserver
Classifier: Development Status :: 4 - Beta
Classifier: Intended Audience :: Developers
Classifier: Topic :: Database
Classifier: Topic :: Software Development :: Libraries :: Python Modules
Classifier: License :: OSI Approved :: MIT License
Classifier: Programming Language :: Python :: 3
Classifier: Programming Language :: Python :: 3.10
Classifier: Programming Language :: Python :: 3.11
Classifier: Programming Language :: Python :: 3.12
Requires-Python: >=3.10
Requires-Dist: mcp>=1.0.0
Requires-Dist: sqlalchemy>=2.0.0
Requires-Dist: python-dotenv>=1.0.0
Provides-Extra: postgres
Requires-Dist: psycopg2-binary>=2.9.0; extra == "postgres"
Provides-Extra: mysql
Requires-Dist: mysql-connector-python>=8.0.0; extra == "mysql"
Provides-Extra: mssql
Requires-Dist: pyodbc>=4.0.0; extra == "mssql"
Provides-Extra: all
Requires-Dist: psycopg2-binary>=2.9.0; extra == "all"
Requires-Dist: mysql-connector-python>=8.0.0; extra == "all"
Requires-Dist: pyodbc>=4.0.0; extra == "all"
Dynamic: author
Dynamic: author-email
Dynamic: classifier
Dynamic: description
Dynamic: description-content-type
Dynamic: home-page
Dynamic: keywords
Dynamic: project-url
Dynamic: provides-extra
Dynamic: requires-dist
Dynamic: requires-python
Dynamic: summary
